{
  "author": "Anne-Marie Beare",
  "authorUrl": "https://www.facebook.com/permalink.php?story_fbid=pfbid0sDSaLKfsZVcdcg48zEVSbFkd9LX1sYgv476qw7pXjHhGVBfSYyCh5G1PbhRZdEWSl&id=859135159",
  "rating": 5,
  "content": "Fantastic food as always, lovely and welcoming staff. Really enjoyed their take away nights and their Philly sandwiches are the best!",
  "date": "2021-04-08T13:53:14.000Z",
  "userId": "fb-pfbid031gn3Y8xrhg8E1",
  "thumbnail": "/images/reviewers/fb-pfbid031gn3Y8xrhg8E1.webp",
  "source": "facebook"
}