{
  "author": "Andrew Veal",
  "authorUrl": "https://www.facebook.com/andrew.veal.52/posts/pfbid02zsBW5W76BvC991FpnC5gUqBcsp4LA3Z94zbudyHDz58HR5z3zcyCdXRMxMsgdM5Pl",
  "rating": 5,
  "content": "A great service was provided by these guys with the hot tub and gazebo!\nA Special thank you to Kane, Liam & Tom for their friendly and efficient service! They were extremely helpful and responsive to our needs and were quick to set us up and then to collect all equipment after hire! \nWould definitely recommend DB Entertainment for their good service! 😁",
  "date": "2021-05-06T08:30:29.000Z",
  "userId": "fb-pfbid0T9YCCnVfEk48ke",
  "thumbnail": "/images/reviewers/fb-pfbid0T9YCCnVfEk48ke.webp",
  "source": "facebook"
}