{
  "author": "Susan Hill",
  "authorUrl": "https://www.google.com/maps/contrib/101779057269820568208?hl=en",
  "rating": 5,
  "content": "Dealing with events I have to rely on outside services delivering on an exact date and time - DB Entertainment have never let me down. They are friendly and reliable, always on time and set up the equipment, explain how it all works and will pick up after the event as arranged. Very professional, would highly recommend",
  "date": "2026-02-26T14:09:33.620Z",
  "userId": "101779057269820568208",
  "thumbnail": "/images/reviewers/101779057269820568208.webp",
  "source": "google"
}